{
  "$schema": "https://ui.shadcn.com/schema/registry-item.json",
  "name": "primitives-effects-fade",
  "type": "registry:ui",
  "title": "Fade",
  "description": "An effect that allows you to animate elements with a fade effect on first view or load.",
  "dependencies": ["motion"],
  "registryDependencies": [
    "@animate-ui/primitives-animate-slot",
    "@animate-ui/hooks-use-is-in-view"
  ],
  "files": [
    {
      "path": "registry/primitives/effects/fade/index.tsx",
      "type": "registry:ui",
      "target": "components/animate-ui/primitives/effects/fade.tsx"
    }
  ]
}
