{
  "$schema": "https://ui.shadcn.com/schema/registry-item.json",
  "name": "icons-loader-pinwheel",
  "type": "registry:ui",
  "title": "Loader Pinwheel Icon",
  "description": "Loader pinwheel icon component.",
  "registryDependencies": ["@animate-ui/icons-icon"],
  "dependencies": ["motion"],
  "files": [
    {
      "path": "registry/icons/loader-pinwheel/index.tsx",
      "type": "registry:ui",
      "target": "components/animate-ui/icons/loader-pinwheel.tsx"
    }
  ],
  "meta": {
    "keywords": [
      "loading",
      "wait",
      "busy",
      "progress",
      "throbber",
      "spinner",
      "spinning",
      "beach ball",
      "frozen",
      "freeze"
    ]
  }
}
