{
  "$schema": "https://ui.shadcn.com/schema/registry-item.json",
  "name": "icons-settings",
  "type": "registry:ui",
  "title": "Settings Icon",
  "description": "Settings icon component.",
  "registryDependencies": ["@animate-ui/icons-icon"],
  "dependencies": ["motion"],
  "files": [
    {
      "path": "registry/icons/settings/index.tsx",
      "type": "registry:ui",
      "target": "components/animate-ui/icons/settings.tsx"
    }
  ],
  "meta": {
    "keywords": ["cog", "edit", "gear", "preferences"]
  }
}
